{"nm":"Card Swipe","ddd":0,"h":500,"w":500,"meta":{"g":"@lottiefiles/creator 1.6.0"},"layers":[{"ty":4,"nm":"Tick","sr":1,"st":0,"op":120,"ip":0,"hd":false,"ln":"Tick","ddd":0,"bm":0,"hasMask":false,"ao":0,"ks":{"a":{"a":0,"k":[333.21250915527344,197.9000015258789]},"s":{"a":1,"k":[{"o":{"x":0,"y":0},"i":{"x":0.36,"y":1},"s":[0,0],"t":37},{"o":{"x":0.22,"y":0.61},"i":{"x":1,"y":1},"s":[134,134],"t":46},{"o":{"x":0.167,"y":0.167},"i":{"x":0.833,"y":0.833},"s":[82,82],"t":55},{"s":[101,101],"t":64}]},"sk":{"a":0,"k":0},"p":{"a":0,"k":[333.21250915527344,197.9000015258789]},"r":{"a":0,"k":0},"sa":{"a":0,"k":0},"o":{"a":1,"k":[{"o":{"x":0.167,"y":0.167},"i":{"x":0.833,"y":0.833},"s":[100],"t":79},{"s":[0],"t":93}]}},"shapes":[{"ty":"gr","bm":0,"ln":"tick","hd":false,"nm":"tick","it":[{"ty":"sh","bm":0,"ln":"tick","hd":false,"nm":"tick","d":1,"ks":{"a":0,"k":{"c":true,"i":[[0,0],[0,0],[0.0999999999999659,-0.09999999999999432],[0,0],[0,0],[0.10000000000002274,-0.19999999999998863],[0,0],[-0.19999999999998863,-0.09999999999999432],[0,0],[0,0],[0,0],[-0.0999999999999659,0.09999999999999432],[0,0],[0,0],[0,0],[0.10000000000002274,0.09999999999999432]],"o":[[0,0],[-0.10000000000002274,-0.09999999999999432],[0,0],[0,0],[-0.19999999999998863,-0.19999999999998863],[0,0],[-0.19999999999998863,0.19999999999998863],[0,0],[0,0],[0,0],[0.10000000000002274,0.09999999999999432],[0,0],[0,0],[0,0],[0.10000000000002274,-0.09999999999999432],[0,0]],"v":[[345.2,191.3],[342.8,188.9],[342.40000000000003,188.9],[329.8,201.5],[324.1,195.8],[323.5,195.8],[321.3,198],[321.3,198.6],[329.5,206.79999999999998],[329.5,206.79999999999998],[329.6,206.89999999999998],[330,206.89999999999998],[330.1,206.79999999999998],[332.3,204.6],[345.2,191.7],[345.2,191.3]]}}},{"ty":"fl","bm":0,"hd":false,"nm":"Fill","c":{"a":0,"k":[1,1,1]},"r":1,"o":{"a":0,"k":100}},{"ty":"tr","a":{"a":0,"k":[0,0]},"s":{"a":0,"k":[100,100]},"sk":{"a":0,"k":0},"p":{"a":0,"k":[0,0]},"r":{"a":0,"k":0},"sa":{"a":0,"k":0},"o":{"a":0,"k":100}}]}],"ind":1},{"ty":4,"nm":"Circle","sr":1,"st":0,"op":300,"ip":0,"hd":false,"ln":"Circle","ddd":0,"bm":0,"hasMask":false,"ao":0,"ks":{"a":{"a":0,"k":[333.3000030517578,197.0999984741211]},"s":{"a":1,"k":[{"o":{"x":0.167,"y":0.167},"i":{"x":0.833,"y":0.833},"s":[0,0],"t":37},{"o":{"x":0.167,"y":0.167},"i":{"x":0.833,"y":0.833},"s":[122,122],"t":46},{"o":{"x":0.167,"y":0.167},"i":{"x":0.833,"y":0.833},"s":[86,86],"t":55},{"s":[102,102],"t":64}]},"sk":{"a":0,"k":0},"p":{"a":0,"k":[333.3000030517578,197.0999984741211]},"r":{"a":0,"k":0},"sa":{"a":0,"k":0},"o":{"a":1,"k":[{"o":{"x":0.167,"y":0.167},"i":{"x":0.833,"y":0.833},"s":[100],"t":78},{"s":[0],"t":93}]}},"shapes":[{"ty":"gr","bm":0,"ln":"circle","hd":false,"nm":"circle","it":[{"ty":"el","bm":0,"ln":"circle","hd":false,"nm":"circle","d":1,"p":{"a":0,"k":[333.3,197.1]},"s":{"a":0,"k":[58.8,58.8]}},{"ty":"fl","bm":0,"hd":false,"nm":"Fill","c":{"a":0,"k":[0.2863,0.9098,0.4941]},"r":1,"o":{"a":0,"k":100}},{"ty":"tr","a":{"a":0,"k":[0,0]},"s":{"a":0,"k":[100,100]},"sk":{"a":0,"k":0},"p":{"a":0,"k":[0,0]},"r":{"a":0,"k":0},"sa":{"a":0,"k":0},"o":{"a":0,"k":100}}]}],"ind":2},{"ty":4,"nm":"Front","sr":1,"st":0,"op":300,"ip":0,"hd":false,"ln":"Front","ddd":0,"bm":0,"hasMask":false,"ao":0,"ks":{"a":{"a":0,"k":[241.25,268.5499954223633]},"s":{"a":0,"k":[100,100]},"sk":{"a":0,"k":0},"p":{"a":0,"k":[241.25,268.5499954223633]},"r":{"a":0,"k":0},"sa":{"a":0,"k":0},"o":{"a":0,"k":100}},"shapes":[{"ty":"gr","bm":0,"hd":false,"nm":"Group 1","it":[{"ty":"sh","bm":0,"hd":false,"nm":"Path 1","d":1,"ks":{"a":0,"k":{"c":true,"i":[[0,0],[0,0],[0,0],[-19,0],[0,0],[0,-19],[0,0]],"o":[[0,0],[0,0],[0,-18.900000000000006],[0,0],[18.899999999999977,0],[0,0],[0,0]],"v":[[308,325.8],[165.5,325.8],[165.5,252.8],[199.8,218.5],[273.8,218.5],[308.1,252.8],[308.1,325.8]]}}},{"ty":"fl","bm":0,"hd":false,"nm":"Fill","c":{"a":0,"k":[0.9451,0.9451,0.9451]},"r":1,"o":{"a":0,"k":100}},{"ty":"tr","a":{"a":0,"k":[0,0]},"s":{"a":0,"k":[100,100]},"sk":{"a":0,"k":0},"p":{"a":0,"k":[0,0]},"r":{"a":0,"k":0},"sa":{"a":0,"k":0},"o":{"a":0,"k":100}}]},{"ty":"gr","bm":0,"hd":false,"nm":"Group 2","it":[{"ty":"sh","bm":0,"hd":false,"nm":"Path 2","d":1,"ks":{"a":0,"k":{"c":true,"i":[[0,0],[0,0],[0,0],[0,0],[-19,0],[0,0],[0,-19],[0,0]],"o":[[0,0],[0,0],[0,0],[0,-18.900000000000006],[0,0],[18.899999999999977,0],[0,0],[0,0]],"v":[[316.9,318.6],[308.09999999999997,325.8],[174.39999999999998,318.6],[174.39999999999998,245.60000000000002],[208.7,211.3],[282.7,211.3],[317,245.60000000000002],[317,318.6]]}}},{"ty":"fl","bm":0,"hd":false,"nm":"Fill","c":{"a":0,"k":[0.7529,0.7843,0.8196]},"r":1,"o":{"a":0,"k":100}},{"ty":"tr","a":{"a":0,"k":[0,0]},"s":{"a":0,"k":[100,100]},"sk":{"a":0,"k":0},"p":{"a":0,"k":[0,0]},"r":{"a":0,"k":0},"sa":{"a":0,"k":0},"o":{"a":0,"k":100}}]}],"ind":3},{"ty":4,"nm":"card","sr":1,"st":0,"op":300,"ip":0,"hd":false,"ln":"card","ddd":0,"bm":0,"hasMask":false,"ao":0,"ks":{"a":{"a":0,"k":[245.5500030517578,252]},"s":{"a":0,"k":[101,101]},"sk":{"a":0,"k":0},"p":{"a":1,"k":[{"o":{"x":0,"y":0},"i":{"x":0.36,"y":1},"s":[246,252],"t":0},{"o":{"x":0.22,"y":0.61},"i":{"x":0.36,"y":1},"s":[136,252],"t":8},{"o":{"x":0.22,"y":0.61},"i":{"x":0.36,"y":1},"s":[249,168],"t":18},{"o":{"x":0.22,"y":0.61},"i":{"x":0.36,"y":1},"s":[316,248],"t":28},{"s":[246,252],"t":35}]},"r":{"a":1,"k":[{"o":{"x":0,"y":0},"i":{"x":0.36,"y":1},"s":[0],"t":0},{"o":{"x":0.22,"y":0.61},"i":{"x":0.36,"y":1},"s":[-15],"t":8},{"o":{"x":0.22,"y":0.61},"i":{"x":0.36,"y":1},"s":[15],"t":18},{"o":{"x":0.22,"y":0.61},"i":{"x":0.36,"y":1},"s":[7],"t":28},{"s":[0],"t":35}]},"sa":{"a":0,"k":0},"o":{"a":0,"k":100}},"shapes":[{"ty":"gr","bm":0,"hd":false,"nm":"Shape Layer 1","it":[{"ty":"gr","bm":0,"hd":false,"nm":"Group 3","it":[{"ty":"rc","bm":0,"hd":false,"nm":"Rectangle 1","d":1,"p":{"a":0,"k":[245.6,271.45]},"r":{"a":0,"k":0},"s":{"a":0,"k":[182.2,22.9]}},{"ty":"fl","bm":0,"hd":false,"nm":"Fill","c":{"a":0,"k":[0.1608,0.2392,0.3059]},"r":1,"o":{"a":0,"k":100}},{"ty":"tr","a":{"a":0,"k":[0,0]},"s":{"a":0,"k":[100,100]},"sk":{"a":0,"k":0},"p":{"a":0,"k":[0,0]},"r":{"a":0,"k":0},"sa":{"a":0,"k":0},"o":{"a":0,"k":100}}]},{"ty":"gr","bm":0,"hd":false,"nm":"Group 4","it":[{"ty":"sh","bm":0,"hd":false,"nm":"Path 3","d":1,"ks":{"a":0,"k":{"c":true,"i":[[0,0],[0,0],[0,9.5],[0,0],[-9.5,0],[0,0],[0,-9.5],[0,0],[9.5,0]],"o":[[0,0],[-9.5,0],[0,0],[0,-9.5],[0,0],[9.5,0],[0,0],[0,9.5],[0,0]],"v":[[319.5,309],[171.6,309],[154.4,291.8],[154.4,212.20000000000002],[171.6,195.00000000000003],[319.5,195.00000000000003],[336.7,212.20000000000002],[336.7,291.8],[319.5,309]]}}},{"ty":"fl","bm":0,"hd":false,"nm":"Fill","c":{"a":0,"k":[0.5608,0.651,0.7804]},"r":1,"o":{"a":0,"k":100}},{"ty":"tr","a":{"a":0,"k":[0,0]},"s":{"a":0,"k":[100,100]},"sk":{"a":0,"k":0},"p":{"a":0,"k":[0,0]},"r":{"a":0,"k":0},"sa":{"a":0,"k":0},"o":{"a":0,"k":100}}]},{"ty":"tr","a":{"a":0,"k":[0,0]},"s":{"a":0,"k":[100,100]},"sk":{"a":0,"k":0},"p":{"a":0,"k":[0,0]},"r":{"a":0,"k":0},"sa":{"a":0,"k":0},"o":{"a":0,"k":100}}]}],"ind":4},{"ty":4,"nm":"Back","sr":1,"st":0,"op":300,"ip":0,"hd":false,"ln":"Back","ddd":0,"bm":0,"hasMask":false,"ao":0,"ks":{"a":{"a":0,"k":[0,0]},"s":{"a":0,"k":[100,100]},"sk":{"a":0,"k":0},"p":{"a":0,"k":[0,0]},"r":{"a":0,"k":0},"sa":{"a":0,"k":0},"o":{"a":0,"k":100}},"shapes":[{"ty":"gr","bm":0,"hd":false,"nm":"Group 5","it":[{"ty":"sh","bm":0,"hd":false,"nm":"Path 4","d":1,"ks":{"a":0,"k":{"c":true,"i":[[0,0],[0,0],[0,0],[0,0],[-19,0],[0,0],[0,-19],[0,0]],"o":[[0,0],[0,0],[0,0],[0,-18.900000000000006],[0,0],[18.899999999999977,0],[0,0],[0,0]],"v":[[324.8,311.9],[316,319.09999999999997],[182.3,311.9],[182.3,238.89999999999998],[216.60000000000002,204.59999999999997],[290.6,204.59999999999997],[324.90000000000003,238.89999999999998],[324.90000000000003,311.9]]}}},{"ty":"fl","bm":0,"hd":false,"nm":"Fill","c":{"a":0,"k":[0.3412,0.3725,0.4235]},"r":1,"o":{"a":0,"k":100}},{"ty":"tr","a":{"a":0,"k":[0,0]},"s":{"a":0,"k":[100,100]},"sk":{"a":0,"k":0},"p":{"a":0,"k":[0,0]},"r":{"a":0,"k":0},"sa":{"a":0,"k":0},"o":{"a":0,"k":100}}]}],"ind":5}],"v":"5.7.0","fr":60,"op":120,"ip":0,"assets":[]}